ncpeek/__init__.py
ncpeek/__main__.py
ncpeek/args/__init__.py
ncpeek/args/arg_parser.py
ncpeek/args/parse_settings.py
ncpeek/args/xpath_parse.py
ncpeek/client.py
ncpeek/devices/devnet_xe_sandbox.json
ncpeek/devices/devnet_xr_sandbox.json
ncpeek/factory/__init__.py
ncpeek/factory/factory_mappings.py
ncpeek/factory/factory_parsers.py
ncpeek/filters/Cisco-IOS-XE-interfaces-oper.xml
ncpeek/filters/Cisco-IOS-XE-memory-oper.xml
ncpeek/filters/Cisco-IOS-XR-facts.xml
ncpeek/filters/Cisco-IOS-XR-hostname.xml
ncpeek/filters/cisco_xe_ietf-interfaces.xml
ncpeek/netconf_devices.py
ncpeek/netconf_parsers.py
ncpeek/netconf_session.py
ncpeek/parsers/__init__.py
ncpeek/parsers/cisco_ios_xe_interfaces_oper.py
ncpeek/parsers/cisco_ios_xe_isis_oper.py
ncpeek/parsers/cisco_ios_xe_memory_oper.py
ncpeek/parsers/cisco_xe_ietf_interfaces.py
ncpeek/parsers/default_parser.py
ncpeek/parsers/remove_namespaces.py
ncpeek/utils/__init__ .py
ncpeek/utils/file_utils.py
ncpeek/utils/text_utils.py
ncpeek-0.1.4.dist-info/LICENSE
ncpeek-0.1.4.dist-info/METADATA
ncpeek-0.1.4.dist-info/WHEEL
ncpeek-0.1.4.dist-info/entry_points.txt
ncpeek-0.1.4.dist-info/RECORD
