Metadata-Version: 2.1
Name: ncpeek
Version: 0.1.4
Summary: ncpeek (short for netconf peek) is a netconf client that retrieves data using the ncclient library.
Home-page: https://github.com/jillesca/ncpeek
License: BSD-3-Clause
Keywords: netconf,ncclient,NETCONF Python client,Cisco,DevNet
Author: Jesus Illescas
Author-email: jillesca@outlook.com
Requires-Python: >=3.11,<4.0
Classifier: Development Status :: 5 - Production/Stable
Classifier: Intended Audience :: Developers
Classifier: License :: OSI Approved :: BSD License
Classifier: Operating System :: OS Independent
Classifier: Programming Language :: Python :: 3
Classifier: Programming Language :: Python :: 3.11
Classifier: Programming Language :: Python :: 3.12
Classifier: Topic :: Software Development :: Libraries :: Python Modules
Classifier: Topic :: System :: Networking
Classifier: Topic :: System :: Networking :: Monitoring
Requires-Dist: ncclient (<=0.6.15)
Requires-Dist: paramiko (<=2.8.1)
Requires-Dist: xmltodict (>=0.13.0,<0.14.0)
Project-URL: Repository, https://github.com/jillesca/ncpeek
